torf_gui/__init__.py
torf_gui/gui.py
torf_gui/ui_about.py
torf_gui/ui_mainwindow.py
torf_gui/version.py
torf_gui-0.4.1.dist-info/LICENSE
torf_gui-0.4.1.dist-info/METADATA
torf_gui-0.4.1.dist-info/WHEEL
torf_gui-0.4.1.dist-info/entry_points.txt
torf_gui-0.4.1.dist-info/top_level.txt
torf_gui-0.4.1.dist-info/RECORD
