Metadata-Version: 2.1
Name: torf-gui
Version: 0.4.1
Summary: An advanced GUI torrent file creator with batch functionality, powered by PyQt and torf.
Home-page: https://github.com/SavageCore/torf-gui
Author: Oliver Sayers
Author-email: talk@savagecore.uk
Keywords: bittorrent torrent
Classifier: Development Status :: 5 - Production/Stable
Classifier: Intended Audience :: End Users/Desktop
Classifier: License :: OSI Approved :: GNU General Public License v3 (GPLv3)
Classifier: Programming Language :: Python :: 3
Classifier: Programming Language :: Python :: 3.8
Classifier: Programming Language :: Python :: 3.9
Classifier: Programming Language :: Python :: 3.10
Classifier: Programming Language :: Python :: 3.11
Classifier: Programming Language :: Python :: 3.12
Classifier: Programming Language :: Python :: 3.13
License-File: LICENSE
Requires-Dist: torf >=4.2.4
Requires-Dist: humanfriendly >=10.0
Requires-Dist: PyQt5 >=5.15.9
Requires-Dist: pyqtdarktheme >=2.1.0
